MANIFEST.in
README.md
setup.cfg
setup.py
marmalade/__init__.py
marmalade/config.py
marmalade/proxies.py
marmalade/timj.py
marmalade/timj_exceptions.py
marmalade/util.py
marmalade.egg-info/PKG-INFO
marmalade.egg-info/SOURCES.txt
marmalade.egg-info/dependency_links.txt
marmalade.egg-info/top_level.txt