Metadata-Version: 1.1
Name: marmalade
Version: 1.1.0
Summary: Python interface to This Is My Jam API.
Home-page: https://github.com/echonest/marmalade
Author: Tyler Williams
Author-email: williams.tyler@gmail.com
License: UNKNOWN
Download-URL: https://github.com/echonest/marmalade
Platform: UNKNOWN
Requires: urllib
Requires: urllib2
Requires: json
